README.md
setup.py
rllibs/__init__.py
rllibs/rltorch/__init__.py
rllibs/rltorch/actor_critic.py
rllibs/rltorch/dqn.py
rllibs/rltorch/ppo.py
rllibs/rltorch/reinforce.py
rllibs/rltorch/rl_utils.py
tests/test.py
zhutools.egg-info/PKG-INFO
zhutools.egg-info/SOURCES.txt
zhutools.egg-info/dependency_links.txt
zhutools.egg-info/top_level.txt